intenc/__init__.py
intenc/pyintenc.cpython-311-x86_64-linux-gnu.so
src/intenc.cpython-311-x86_64-linux-gnu.so
src/intenc/bpe.cpython-311-x86_64-linux-gnu.so
src/intenc/ne.cpython-311-x86_64-linux-gnu.so
src/intenc/utils.cpython-311-x86_64-linux-gnu.so
tests/tintenc.cpython-311-x86_64-linux-gnu.so
intenc-0.1.0.dist-info/METADATA
intenc-0.1.0.dist-info/WHEEL
intenc-0.1.0.dist-info/top_level.txt
intenc-0.1.0.dist-info/RECORD
