Metadata-Version: 2.1
Name: intenc
Version: 0.1.0
Summary: Integer encoding
Home-page: https://github.com/thatrandomperson5/BOE
Author: thatrandomperson5
